README.md
setup.cfg
setup.py
ssi_fctrading/__init__.py
ssi_fctrading/fc_client.py
ssi_fctrading/fc_stream.py
ssi_fctrading/version.py
ssi_fctrading.egg-info/PKG-INFO
ssi_fctrading.egg-info/SOURCES.txt
ssi_fctrading.egg-info/dependency_links.txt
ssi_fctrading.egg-info/requires.txt
ssi_fctrading.egg-info/top_level.txt
ssi_fctrading/constant/__init__.py
ssi_fctrading/constant/api.py
ssi_fctrading/core/__init__.py
ssi_fctrading/core/core_crypto.py
ssi_fctrading/core/core_helper.py
ssi_fctrading/models/AccessTokenModel.py
ssi_fctrading/models/Requests.py
ssi_fctrading/models/Responses.py
ssi_fctrading/models/__init__.py
ssi_fctrading/signalr/__init__.py
ssi_fctrading/signalr/_connection.py
ssi_fctrading/signalr/helpers.py
ssi_fctrading/signalr/events/__init__.py
ssi_fctrading/signalr/events/_events.py
ssi_fctrading/signalr/hubs/__init__.py
ssi_fctrading/signalr/hubs/_hub.py
ssi_fctrading/signalr/hubs/errors.py
ssi_fctrading/signalr/transports/__init__.py
ssi_fctrading/signalr/transports/_exceptions.py
ssi_fctrading/signalr/transports/_parameters.py
ssi_fctrading/signalr/transports/_queue_events.py
ssi_fctrading/signalr/transports/_transport.py
ssi_fctrading/signalr/transports/base_transport.py
ssi_fctrading/signalr/transports/connection.py
ssi_fctrading/signalr/transports/reconnection.py