Metadata-Version: 2.1
Name: ssi-fctrading
Version: 2.4.1
Summary: FastConnect TradingAPI client by Python
Home-page: https://github.com/SSI-Securities-Corporation/python-fctrading
Author: ducdv
Author-email: ducdv@ssi.com.vn
License: MIT
Platform: POSIX
Platform: Windows
Classifier: Programming Language :: Python
Classifier: Programming Language :: Python :: 3
Classifier: Programming Language :: Python :: 3.6
Classifier: Programming Language :: Python :: 3.7
Classifier: Programming Language :: Python :: 3.8
Classifier: Programming Language :: Python :: 3.9
Requires-Python: >=3.7
